recurse_words/__init__.py
recurse_words/corpi.py
recurse_words/graph.py
recurse_words/recursers/__init__.py
recurse_words/recursers/graph.py
recurse_words/recursers/recurser.py
recurse_words-0.2.1.dist-info/LICENSE
recurse_words-0.2.1.dist-info/WHEEL
recurse_words-0.2.1.dist-info/METADATA
recurse_words-0.2.1.dist-info/RECORD
