Metadata-Version: 2.1
Name: recurse-words
Version: 0.2.1
Summary: find words that have other words in them that when you take the inner words out what's left is still a word
Home-page: https://github.com/sneakers-the-rat/recurse-words
License: Unlicense
Author: sneakers-the-rat
Author-email: JLSaunders987@gmail.com
Requires-Python: >=3.7,<4.0
Classifier: License :: Other/Proprietary License
Classifier: Programming Language :: Python :: 3
Classifier: Programming Language :: Python :: 3.10
Classifier: Programming Language :: Python :: 3.7
Classifier: Programming Language :: Python :: 3.8
Classifier: Programming Language :: Python :: 3.9
Provides-Extra: docs
Requires-Dist: autodocsumm (>=0.2.2,<0.3.0); extra == "docs"
Requires-Dist: datashader (>=0.12.1,<0.13.0)
Requires-Dist: furo (>=2021.4.11-beta.34,<2022.0.0); extra == "docs"
Requires-Dist: holoviews (>=1.14.3,<2.0.0)
Requires-Dist: ipykernel (>=5.5.3,<6.0.0)
Requires-Dist: networkx (>=2.6.3,<3.0.0)
Requires-Dist: pygraphviz (>=1.7,<2.0)
Requires-Dist: requests (>=2.25.1,<3.0.0)
Requires-Dist: scikit-image (>=0.18.1,<0.19.0)
Requires-Dist: sphinx (>=3.5.4,<4.0.0); extra == "docs"
Requires-Dist: tqdm (>=4.60.0,<5.0.0)
Requires-Dist: wheel (>=0.36.2,<0.37.0)
Project-URL: Repository, https://github.com/sneakers-the-rat/recurse-words
